{"updates":[{"id":"recWfIVIBl98RROVV","headline":"UAE launches Phase 1 of R&D Tax Incentives Programme","summary":"","source_name":"WAM","category":"General","published_date":"2026-03-19"},{"id":"recnocwFc9CYsk5Wv","headline":"BREAKING: Thursday completes Ramadan; Friday marks first day of Eid Al-Fitr in UAE: Presidential Court The Presidential Court has announced that Thursday will complete the Holy Month of Ramadan, and F","summary":"","source_name":"WAM","category":"Legal","published_date":"2026-03-19"},{"id":"recYYwKMbVN7fGyGH","headline":"MoFA, in coordination with NCEMA, continues to implement evacuation plans, facilitate return of around 500 UAE Golden Visa holders and residents stranded abroad","summary":"","source_name":"WAM","category":"Visa","published_date":"2026-03-18"},{"id":"recaJvQH8PILEK55i","headline":"RAKEZ hosts workshop on UAE corporate tax, financial management","summary":"","source_name":"WAM","category":"General","published_date":"2026-03-18"},{"id":"recbZLZVlfGgnJULz","headline":"S. Korea posts fiscal surplus of 11.3 tln won in January on increased tax revenue","summary":"","source_name":"WAM","category":"General","published_date":"2026-03-18"}]}